build/lib/tests/test_graph.py
build/lib/tests/test_interval.py
build/lib/tests/test_measurement_correction.py
build/lib/wath/__init__.py
build/lib/wath/interval.py
build/lib/wath/prime.py
build/lib/wath/version.py
build/lib/wath/fit/__init__.py
build/lib/wath/fit/delay.py
build/lib/wath/fit/geo.py
build/lib/wath/fit/peak.py
build/lib/wath/fit/resonator.py
build/lib/wath/fit/simple.py
build/lib/wath/fit/spectrum.py
build/lib/wath/fit/symmetry.py
build/lib/wath/graph/__init__.py
build/lib/wath/graph/mst.py
build/lib/wath/markov/__init__.py
build/lib/wath/markov/viterbi.py
build/lib/wath/measure/__init__.py
build/lib/wath/measure/correction.py
build/lib/wath/measure/demodulate.py
build/lib/wath/measure/readout.py
build/lib/wath/scqubits/__init__.py
build/lib/wath/scqubits/transmon.py
build/lib/wath/signal/__init__.py
build/lib/wath/signal/distortion.py
build/lib/wath/signal/func.py
build/lib/wath/signal/noise.py
build/lib/wath/utils/__init__.py
build/lib/wath/utils/fibheap.py
tests/test_graph.py
tests/test_interval.py
tests/test_measurement_correction.py
wath/__init__.py
wath/interval.py
wath/prime.py
wath/version.py
wath/fit/__init__.py
wath/fit/delay.py
wath/fit/geo.py
wath/fit/peak.py
wath/fit/resonator.py
wath/fit/simple.py
wath/fit/spectrum.py
wath/fit/symmetry.py
wath/graph/__init__.py
wath/graph/mst.py
wath/markov/__init__.py
wath/markov/viterbi.py
wath/measure/__init__.py
wath/measure/correction.py
wath/measure/demodulate.py
wath/measure/readout.py
wath/scqubits/__init__.py
wath/scqubits/transmon.py
wath/signal/__init__.py
wath/signal/distortion.py
wath/signal/func.py
wath/signal/noise.py
wath/utils/__init__.py
wath/utils/fibheap.py
wath-1.2.2.dist-info/licenses/LICENSE
wath-1.2.2.dist-info/METADATA
wath-1.2.2.dist-info/WHEEL
wath-1.2.2.dist-info/top_level.txt
wath-1.2.2.dist-info/RECORD
