Metadata-Version: 2.4
Name: wath
Version: 1.2.2
Summary: tools for waveforms
Author-email: feihoo87 <feihoo87@gmail.com>
Maintainer-email: feihoo87 <feihoo87@gmail.com>
Project-URL: Homepage, https://github.com/feihoo87/wath
Project-URL: Bug Reports, https://github.com/feihoo87/wath/issues
Project-URL: Source, https://github.com/feihoo87/wath/
Keywords: waveforms,quantum
Classifier: Development Status :: 3 - Alpha
Classifier: Intended Audience :: Developers
Classifier: Intended Audience :: Science/Research
Classifier: Operating System :: Microsoft :: Windows
Classifier: Operating System :: POSIX :: Linux
Classifier: Operating System :: MacOS :: MacOS X
Classifier: Topic :: Scientific/Engineering :: Mathematics
Classifier: Topic :: Scientific/Engineering :: Physics
Classifier: Programming Language :: Python
Classifier: Programming Language :: Python :: 3.10
Classifier: Programming Language :: Python :: 3.11
Classifier: Programming Language :: Python :: 3.12
Requires-Python: >=3.10
License-File: LICENSE
Requires-Dist: lmfit>=1.2.2
Requires-Dist: matplotlib>=3.7.2
Requires-Dist: numpy>=1.25.1
Requires-Dist: pycycles>=1.0.5
Requires-Dist: scikit-learn>=1.3.0
Requires-Dist: scikit-optimize>=0.9.0
Requires-Dist: scipy>=1.11.1
Requires-Dist: waveforms>=1.9.4
Dynamic: license-file
